{
  "editor:set-heading-1": [
    {
      "modifiers": [
        "Alt"
      ],
      "key": "1"
    }
  ],
  "editor:set-heading-2": [
    {
      "modifiers": [
        "Alt"
      ],
      "key": "2"
    }
  ],
  "editor:set-heading-3": [
    {
      "modifiers": [
        "Alt"
      ],
      "key": "3"
    }
  ],
  "file-explorer:new-file-in-new-pane": [
    {
      "modifiers": [
        "Alt"
      ],
      "key": "N"
    }
  ],
  "canvas:new-file": [
    {
      "modifiers": [
        "Alt"
      ],
      "key": "O"
    }
  ],
  "app:open-vault": [
    {
      "modifiers": [
        "Alt"
      ],
      "key": "L"
    }
  ]
}